.DS_Store
rbatools/__init__.py
rbatools/_authors.py
rbatools/_auxiliary_functions.py
rbatools/_credits.py
rbatools/_version.py
rbatools/_warnings_and_errors.py
rbatools/compartment_block.py
rbatools/data_block.py
rbatools/density_constraint_block.py
rbatools/description_block.py
rbatools/enzyme_block.py
rbatools/enzyme_constraint_block.py
rbatools/fba_problem.py
rbatools/info_matrix.py
rbatools/information_block.py
rbatools/macromolecule_block.py
rbatools/metabolite_block.py
rbatools/metabolite_constraint_block.py
rbatools/module_block.py
rbatools/parameter_block.py
rbatools/process_block.py
rbatools/process_constraint_block.py
rbatools/protein_block.py
rbatools/rba_lp.py
rbatools/rba_model_structure.py
rbatools/rba_problem.py
rbatools/rba_problem_matrix.py
rbatools/rba_session.py
rbatools/rba_simulation_data.py
rbatools/rba_simulation_parameters.py
rbatools/reaction_block.py
rbatools/statistics_block.py
rbatools/target_block.py
rbatools/cli/__init__.py
rbatools/cli/generate_sbtab_of_model_for_html.py
rbatools/cli/run_growth_rate_optimization.py
rbatools-1.0.3.dist-info/LICENSE.txt
rbatools-1.0.3.dist-info/METADATA
rbatools-1.0.3.dist-info/WHEEL
rbatools-1.0.3.dist-info/entry_points.txt
rbatools-1.0.3.dist-info/top_level.txt
rbatools-1.0.3.dist-info/RECORD
