Metadata-Version: 2.1
Name: rbatools
Version: 1.0.3
Summary: Programming interface to resource allocation modelling with the Resource Balance Analysis (RBA) method.
Home-page: https://rba.inrae.fr
Author: Oliver Bodeit, Anne Goelzer & Wolfram Liebermeister
Author-email: anne.goelzer@inrae.fr, wolfram.liebermeister@inrae.fr
License: GPLv3
Keywords: metabolism,resource allocation modellingResource Balance Analysis,molecular biology,cell biology,biochemistry,systems biology,computational biology,mathematical modeling,numerical simulation
Platform: UNKNOWN
Classifier: Development Status :: 3 - Alpha
Classifier: Intended Audience :: Science/Research
Classifier: Topic :: Scientific/Engineering
Classifier: Topic :: Scientific/Engineering :: Bio-Informatics
Classifier: License :: OSI Approved :: GNU General Public License v3 (GPLv3)
Classifier: Programming Language :: Python :: 3
License-File: LICENSE.txt
Requires-Dist: rbapy
Requires-Dist: swiglpk
Requires-Dist: sbtab (==1.0.6)
Requires-Dist: jxmlease
Requires-Dist: urllib3
